ngspice-nghdl/src/xspice/icm/ghdl/decoder/DUTghdl/decoder.vhdl
library IEEE;
use IEEE.STD_LOGIC_1164.ALL;

entity decoder is
Port ( sel : in STD_LOGIC_VECTOR (2 downto 0);
y : out STD_LOGIC_VECTOR (7 downto 0));
end decoder;

architecture Behavioral of decoder is
begin
with sel select
y<="00000001" when "000",
"00000010" when "001",
"00000100" when "010",
"00001000" when "011",
"00010000" when "100",
"00100000" when "101",
"01000000" when "110",
"10000000" when "111",
"00000000" when others;
end Behavioral;

ngspice-nghdl/src/xspice/icm/ghdl/decoder/DUTghdl/decoder_tb.vhdl
--------------------------------------------------------------------------------
--This testbench has been created by Ambikeshwar Srivastava, Rahul Paknikar 
--------------------------- FOSSEE, IIT Bombay ---------------------------------
--------------------------------------------------------------------------------

        library ieee;
        use ieee.std_logic_1164.all;
        use ieee.numeric_std.all;
        library work;
        use work.Vhpi_Foreign.all;
        use work.Utility_Package.all;
        use work.sock_pkg.all;

        entity decoder_tb is
end entity;

architecture decoder_tb_beh of decoder_tb is
	component decoder is
		port(
				sel: in std_logic_vector(2 downto 0);
				y: out std_logic_vector(7 downto 0)
				);
	end component;

	signal clk_s : std_logic := '0';
	signal sel: std_logic_vector(2 downto 0);
	signal y: std_logic_vector(7 downto 0);


begin

	u1 : decoder port map(
				sel => sel,
				y => y
			);
	clk_s <= not clk_s after 5 us;

process
		variable sock_port : integer;
		type string_ptr is access string;
		variable sock_ip : string_ptr;
		begin
		sock_port := sock_port_fun;
		sock_ip := new string'(sock_ip_fun);
		Vhpi_Initialize(sock_port,Pack_String_To_Vhpi_String(sock_ip.all));
		wait until clk_s = '1';
		while true loop
			wait until clk_s = '0';
			Vhpi_Listen;
			wait for 1 us;
			Vhpi_Send;
		end loop;
		wait;
	end process;

	process
		variable count : integer:=0;
		variable sel_v : VhpiString;
		variable y_v : VhpiString;
		variable obj_ref : VhpiString;
	begin
		while true loop
			wait until clk_s = '0';

			obj_ref := Pack_String_To_Vhpi_String("sel");
			Vhpi_Get_Port_Value(obj_ref,sel_v,3);
			sel <= Unpack_String(sel_v,3);

			wait for 1 us;
			y_v := Pack_String_To_Vhpi_String(Convert_SLV_To_String(y));
			obj_ref := Pack_String_To_Vhpi_String("y");
			Vhpi_Set_Port_Value(obj_ref,y_v,8);

			report "Iteration - "& integer'image(count) severity note;
			count := count + 1;
		end loop;
	end process;

end architecture;

ngspice-nghdl/src/xspice/icm/ghdl/decoder/DUTghdl/decoder_tb.vcd
$date
  Mon Dec 20 01:44:01 2021
$end
$version
  GHDL v0
$end
$timescale
  1 fs
$end
$scope module standard $end
$upscope $end
$scope module std_logic_1164 $end
$upscope $end
$scope module numeric_std $end
$upscope $end
$scope module utility_package $end
$upscope $end
$scope module vhpi_foreign $end
$upscope $end
$scope module sock_pkg $end
$upscope $end
$scope module decoder_tb $end
$var reg 1 ! clk_s $end
$var reg 3 " sel[2:0] $end
$var reg 8 # y[7:0] $end
$scope module u1 $end
$var reg 3 $ sel[2:0] $end
$var reg 8 % y[7:0] $end
$upscope $end
$upscope $end
$enddefinitions $end
#0
0!
bUUU "
b00000000 #
bUUU $
b00000000 %
#5000000000
1!
#10000000000
0!
b000 "
b00000001 #
b000 $
b00000001 %
#11000000000
#15000000000
1!
#20000000000
0!
#21000000000
#25000000000
1!
#30000000000
0!
b001 "
b00000010 #
b001 $
b00000010 %
#31000000000
#35000000000
1!
#40000000000
0!
b010 "
b00000100 #
b010 $
b00000100 %
#41000000000
#45000000000
1!
#50000000000
0!
b011 "
b00001000 #
b011 $
b00001000 %
#51000000000
#55000000000
1!
#60000000000
0!
b100 "
b00010000 #
b100 $
b00010000 %
#61000000000
#65000000000
1!
#70000000000
0!
b101 "
b00100000 #
b101 $
b00100000 %
#71000000000
#75000000000
1!
#80000000000
0!
b110 "
b01000000 #
b110 $
b01000000 %
#81000000000
#85000000000
1!
#90000000000
0!
b111 "
b10000000 #
b111 $
b10000000 %
#91000000000
#95000000000
1!
#100000000000
0!
b000 "
b00000001 #
b000 $
b00000001 %
#101000000000
#105000000000
1!
#110000000000
0!
b001 "
b00000010 #
b001 $
b00000010 %
#111000000000
#115000000000
1!
#120000000000
0!
b010 "
b00000100 #
b010 $
b00000100 %
#121000000000
#125000000000
1!
#130000000000
0!
b011 "
b00001000 #
b011 $
b00001000 %
#131000000000
#135000000000
1!
#140000000000
0!
b100 "
b00010000 #
b100 $
b00010000 %
#141000000000
#145000000000
1!
#150000000000
0!
b101 "
b00100000 #
b101 $
b00100000 %
#151000000000
#155000000000
1!
#160000000000
0!
b110 "
b01000000 #
b110 $
b01000000 %
