ngspice-nghdl/src/xspice/icm/ghdl/pwmd/DUTghdl/pwmd.vhdl
library ieee;
use ieee.std_logic_1164.all;
use ieee.numeric_std.all;

entity pwmdecrement is
port(C, D : in std_logic;
     Q : out std_logic);
end pwmdecrement;


architecture bhv of pwmdecrement is
        signal count: integer:=0;       
        signal alpha: integer:=0;  --counts number of clocks
        signal beta : integer:=1;  --counts number of times 'D' is low w.r.t Clock signal(C)  
        signal tmp  : integer:=9; --stores the value of beta for which Q will be set HIGH
        begin
	process (C,D)

        begin
        if(C='1' and C'event) then
        alpha<=alpha+1;  --counts number of rising edges
                if(count=0) then --initial pulse 
                Q <= '1';
                count<=1;
                end if;
               if(D='0') then --if D is low, increase beta by 1
                beta<=beta+1;
                end if;
                if(alpha=9) then --when aplha is 9, decrease beta by 1 and store in tmp //--set to 9 on purpose(so that first pwm signal has 90% duty cycle)
                tmp<=beta-1; --decrease beta and store in tmp, so that we get 10% less duty cycle than previous
                alpha<=0;
                beta<=0;
                count<=0;
                end if;
                if(tmp=alpha) then --the moment when number of clocks(alpha) equals previous number of times Q was high(tmp), we turn Q off. 
                Q<='0';
                end if;
        end if;
        end process;
end bhv;

ngspice-nghdl/src/xspice/icm/ghdl/pwmdecrement/DUTghdl/pwmdecrement_tb.vhdl
--------------------------------------------------------------------------------
--This testbench has been created by Ambikeshwar Srivastava, Rahul Paknikar 
--------------------------- FOSSEE, IIT Bombay ---------------------------------
--------------------------------------------------------------------------------

        library ieee;
        use ieee.std_logic_1164.all;
        use ieee.numeric_std.all;
        library work;
        use work.Vhpi_Foreign.all;
        use work.Utility_Package.all;
        use work.sock_pkg.all;

        entity pwmdecrement_tb is
end entity;

architecture pwmdecrement_tb_beh of pwmdecrement_tb is
	component pwmdecrement is
		port(
				C: in std_logic;
				D: in std_logic;
				Q: out std_logic
				);
	end component;

	signal clk_s : std_logic := '0';
	signal C: std_logic;
	signal D: std_logic;
	signal Q: std_logic;


begin

	u1 : pwmdecrement port map(
				C => C,
				D => D,
				Q => Q
			);
	clk_s <= not clk_s after 5 us;

process
		variable sock_port : integer;
		type string_ptr is access string;
		variable sock_ip : string_ptr;
		begin
		sock_port := sock_port_fun;
		sock_ip := new string'(sock_ip_fun);
		Vhpi_Initialize(sock_port,Pack_String_To_Vhpi_String(sock_ip.all));
		wait until clk_s = '1';
		while true loop
			wait until clk_s = '0';
			Vhpi_Listen;
			wait for 1 us;
			Vhpi_Send;
		end loop;
		wait;
	end process;

	process
		variable count : integer:=0;
		variable C_v : VhpiString;
		variable D_v : VhpiString;
		variable Q_v : VhpiString;
		variable obj_ref : VhpiString;
	begin
		while true loop
			wait until clk_s = '0';

			obj_ref := Pack_String_To_Vhpi_String("C");
			Vhpi_Get_Port_Value(obj_ref,C_v,1);
			C <= To_Std_Logic(C_v);

			obj_ref := Pack_String_To_Vhpi_String("D");
			Vhpi_Get_Port_Value(obj_ref,D_v,1);
			D <= To_Std_Logic(D_v);

			wait for 1 us;
			Q_v := Pack_String_To_Vhpi_String(To_String(Q));
			obj_ref := Pack_String_To_Vhpi_String("Q");
			Vhpi_Set_Port_Value(obj_ref,Q_v,1);

			report "Iteration - "& integer'image(count) severity note;
			count := count + 1;
		end loop;
	end process;

end architecture;

ngspice-nghdl/src/xspice/icm/ghdl/pwmdecrement/DUTghdl/pwmdecrement_tb.vcd
$date
  Sat Oct 16 13:09:05 2021
$end
$version
  GHDL v0
$end
$timescale
  1 fs
$end
$scope module standard $end
$upscope $end
$scope module std_logic_1164 $end
$upscope $end
$scope module numeric_std $end
$upscope $end
$scope module utility_package $end
$upscope $end
$scope module vhpi_foreign $end
$upscope $end
$scope module sock_pkg $end
$upscope $end
$scope module pwmdecrement_tb $end
$var reg 1 ! clk_s $end
$var reg 1 " c $end
$var reg 1 # d $end
$var reg 1 $ q $end
$scope module u1 $end
$var reg 1 % c $end
$var reg 1 & d $end
$var reg 1 ' q $end
$var integer 32 ( count $end
$var integer 32 ) alpha $end
$var integer 32 * beta $end
$var integer 32 + tmp $end
$upscope $end
$upscope $end
$enddefinitions $end
#0
0!
U"
U#
U$
U%
U&
U'
b0 (
b0 )
b1 *
b1001 +
#5000000000
1!
#10000000000
0!
0"
0#
0%
0&
#11000000000
#15000000000
1!
#20000000000
0!
#21000000000
#25000000000
1!
#30000000000
0!
1#
1&
#31000000000
#35000000000
1!
#40000000000
0!
1"
1$
1%
1'
b1 (
b1 )
#41000000000
#45000000000
1!
#50000000000
0!
#51000000000
#55000000000
1!
#60000000000
0!
0"
0%
#61000000000
#65000000000
1!
#70000000000
0!
0#
0&
#71000000000
#75000000000
1!
#80000000000
0!
1"
1%
b10 )
b10 *
#81000000000
#85000000000
1!
#90000000000
0!
#91000000000
#95000000000
1!
#100000000000
0!
#101000000000
#105000000000
1!
#110000000000
0!
0"
0%
#111000000000
#115000000000
1!
#120000000000
0!
1"
1%
b11 )
b11 *
#121000000000
#125000000000
1!
#130000000000
0!
#131000000000
#135000000000
1!
#140000000000
0!
#141000000000
#145000000000
1!
#150000000000
0!
0"
0%
